feature_graph/__init__.py
feature_graph/base.py
feature_graph/bigquery_node.py
feature_graph-0.2.0.dist-info/WHEEL
feature_graph-0.2.0.dist-info/METADATA
feature_graph-0.2.0.dist-info/RECORD
